README.md
setup.cfg
setup.py
typedb_ml/__init__.py
typedb_ml.egg-info/PKG-INFO
typedb_ml.egg-info/SOURCES.txt
typedb_ml.egg-info/dependency_links.txt
typedb_ml.egg-info/not-zip-safe
typedb_ml.egg-info/requires.txt
typedb_ml.egg-info/top_level.txt
typedb_ml/networkx/__init__.py
typedb_ml/networkx/concept_dict_to_networkx.py
typedb_ml/networkx/iterate.py
typedb_ml/networkx/queries_to_networkx.py
typedb_ml/networkx/query_graph.py
typedb_ml/pytorch_geometric/__init__.py
typedb_ml/pytorch_geometric/dataset/__init__.py
typedb_ml/pytorch_geometric/dataset/dataset.py
typedb_ml/pytorch_geometric/transform/__init__.py
typedb_ml/pytorch_geometric/transform/binary_link_prediction.py
typedb_ml/pytorch_geometric/transform/common.py
typedb_ml/pytorch_geometric/transform/encode.py
typedb_ml/typedb/__init__.py
typedb_ml/typedb/load.py
typedb_ml/typedb/thing.py
typedb_ml/typedb/type.py
typedb_ml/typedb/test/__init__.py
typedb_ml/typedb/test/base.py
typedb_ml/typedb/test/mock/__init__.py
typedb_ml/typedb/test/mock/answer.py
typedb_ml/typedb/test/mock/concept.py