Metadata-Version: 2.1
Name: typedb-ml
Version: 0.3.0
Summary: A Machine Learning Library for TypeDB.
Home-page: https://github.com/vaticle/typedb-ml
Author: Vaticle
Author-email: community@vaticle.com
License: Apache-2.0
Keywords: machine learning logical reasoning knowledege graph typedb database graph knowledgebase knowledge-engineering
Platform: UNKNOWN
Classifier: Programming Language :: Python :: 3
Classifier: Programming Language :: Python :: 3.7
Classifier: License :: OSI Approved :: Apache Software License
Classifier: Operating System :: OS Independent
Classifier: Intended Audience :: Developers
Classifier: Intended Audience :: Science/Research
Classifier: Topic :: Scientific/Engineering
Classifier: Topic :: Scientific/Engineering :: Information Analysis
Classifier: Topic :: Scientific/Engineering :: Artificial Intelligence
Classifier: Topic :: Software Development :: Libraries
Classifier: Topic :: Software Development :: Libraries :: Python Modules
